minchin/jrnl/DayOneJournal.py
minchin/jrnl/EncryptedJournal.py
minchin/jrnl/Entry.py
minchin/jrnl/FolderJournal.py
minchin/jrnl/Journal.py
minchin/jrnl/__main__.py
minchin/jrnl/__version__.py
minchin/jrnl/args.py
minchin/jrnl/behave_testing.py
minchin/jrnl/cli.py
minchin/jrnl/color.py
minchin/jrnl/commands.py
minchin/jrnl/config.py
minchin/jrnl/constants.py
minchin/jrnl/editor.py
minchin/jrnl/exception.py
minchin/jrnl/install.py
minchin/jrnl/jrnl.py
minchin/jrnl/os_compat.py
minchin/jrnl/output.py
minchin/jrnl/prompt.py
minchin/jrnl/time.py
minchin/jrnl/upgrade.py
minchin/jrnl/plugins/base.py
minchin/jrnl/plugins/meta.py
minchin/jrnl/plugins/util.py
minchin/jrnl/plugins/exporter/dates.py
minchin/jrnl/plugins/exporter/fancy.py
minchin/jrnl/plugins/exporter/json.py
minchin/jrnl/plugins/exporter/markdown.py
minchin/jrnl/plugins/exporter/pelican.py
minchin/jrnl/plugins/exporter/pretty.py
minchin/jrnl/plugins/exporter/short.py
minchin/jrnl/plugins/exporter/tag.py
minchin/jrnl/plugins/exporter/text.py
minchin/jrnl/plugins/exporter/xml.py
minchin/jrnl/plugins/exporter/yaml.py
minchin/jrnl/plugins/importer/jrnl.py
minchin.jrnl-7.1.0.dist-info/LICENSE.rst
minchin.jrnl-7.1.0.dist-info/METADATA
minchin.jrnl-7.1.0.dist-info/WHEEL
minchin.jrnl-7.1.0.dist-info/entry_points.txt
minchin.jrnl-7.1.0.dist-info/top_level.txt
minchin.jrnl-7.1.0.dist-info/RECORD
