Metadata-Version: 2.1
Name: minchin.jrnl
Version: 7.1.0
Summary: Manage and record your thoughts, in plain text.
Author-email: Manuel Ebert <manuel@1450.me>, Jonathan Wren <jonathan@nowandwren.com>, Micah Ellison <micahellison@gmail.com>, William Minchin <w_minchin@hotmail.com>
Maintainer-email: William Minchin <w_minchin@hotmail.com>
License: GPLv3
Project-URL: Homepage, http://minchin.ca/minchin.jrnl/
Project-URL: Bug Tracker, https://github.com/MinchinWeb/minchin.jrnl/issues
Project-URL: Documentation, http://minchin.ca/minchin.jrnl/
Project-URL: Repository, https://github.com/MinchinWeb/minchin.jrnl
Project-URL: Changelog, http://minchin.ca/minchin.jrnl/changelog/
Project-URL: Release Notes, https://blog.minchin.ca/label/minchinjrnl/
Classifier: Development Status :: 5 - Production/Stable
Classifier: Environment :: Console
Classifier: Intended Audience :: End Users/Desktop
Classifier: License :: OSI Approved :: GNU General Public License v3 (GPLv3)
Classifier: Operating System :: OS Independent
Classifier: Programming Language :: Python :: 3
Classifier: Programming Language :: Python :: 3.8
Classifier: Programming Language :: Python :: 3.9
Classifier: Programming Language :: Python :: 3.10
Classifier: Programming Language :: Python :: 3.11
Classifier: Topic :: Office/Business :: News/Diary
License-File: LICENSE.rst
Requires-Dist: colorama >=0.4
Requires-Dist: cryptography >=41.0.4
Requires-Dist: keyring >=21.0
Requires-Dist: parsedatetime >=2.6
Requires-Dist: platformdirs >=3
Requires-Dist: python-dateutil >=2.8
Requires-Dist: pyxdg >=0.27.0
Requires-Dist: pyyaml >=5.1
Requires-Dist: rich
Requires-Dist: tzlocal >=4
Requires-Dist: backports.zoneinfo ; python_version < "3.9"
Provides-Extra: dev
Requires-Dist: pip-tools >=7 ; extra == 'dev'
Requires-Dist: invoke ; extra == 'dev'
Requires-Dist: black >=23.9 ; extra == 'dev'
Requires-Dist: isort ; extra == 'dev'
Requires-Dist: flake8 ; extra == 'dev'
Requires-Dist: flake8-pyproject ; extra == 'dev'
Requires-Dist: behave >=1.2 ; extra == 'dev'
Requires-Dist: toml >=0.10 ; extra == 'dev'
Requires-Dist: pytest >=6.2 ; extra == 'dev'
Provides-Extra: docs
Requires-Dist: sphinx ; extra == 'docs'
Requires-Dist: releases ; extra == 'docs'
Provides-Extra: release
Requires-Dist: invoke ; extra == 'release'
Requires-Dist: minchin.releaser >=0.9.0 ; extra == 'release'
Requires-Dist: semantic-version <2.7 ; extra == 'release'
